remoteenv/__init__.py
remoteenv/env.py
remoteenv/exceptions.py
remoteenv/backends/__init__.py
remoteenv/backends/base.py
remoteenv/backends/zk.py
venv/bin/activate_this.py
pyremoteenv-0.2.5.dist-info/LICENSE
pyremoteenv-0.2.5.dist-info/METADATA
pyremoteenv-0.2.5.dist-info/WHEEL
pyremoteenv-0.2.5.dist-info/top_level.txt
pyremoteenv-0.2.5.dist-info/RECORD
