Metadata-Version: 2.1
Name: pyremoteenv
Version: 0.2.5
Summary: Remote env for python
Author-email: Roman Medvedev <pypi@romavm.dev>
License: MIT License
Project-URL: Homepage, https://github.com/Romamo/pyremoteenv
Keywords: zookeeper,config-management,remote,environment,kazoo
Classifier: Development Status :: 3 - Alpha
Classifier: Intended Audience :: Developers
Classifier: Programming Language :: Python :: 3
Classifier: License :: OSI Approved :: MIT License
Classifier: Operating System :: OS Independent
Classifier: Topic :: Software Development :: Libraries :: Python Modules
Requires-Python: >=3.9
License-File: LICENSE
Provides-Extra: zk
Requires-Dist: kazoo; extra == "zk"
